<?xml version="1.0" encoding="UTF-8"?>
<!DOCTYPE mapper PUBLIC "-//mybatis.org//DTD Mapper 3.0//EN" "http://mybatis.org/dtd/mybatis-3-mapper.dtd">
<mapper namespace="com.nicefish.mapper.PostMapper">
  <resultMap id="BaseResultMap" type="com.nicefish.model.Post">
    <!--
      WARNING - @mbg.generated
      This element is automatically generated by MyBatis Generator, do not modify.
    -->
    <id column="POST_ID" jdbcType="VARCHAR" property="postId" />
    <result column="POST_TITLE" jdbcType="VARCHAR" property="postTitle" />
    <result column="POST_TIME" jdbcType="TIMESTAMP" property="postTime" />
    <result column="ORIGINAL_URL" jdbcType="VARCHAR" property="originalUrl" />
    <result column="POST_TYPE" jdbcType="INTEGER" property="postType" />
    <result column="LAST_MODIFY_TIME" jdbcType="TIMESTAMP" property="lastModifyTime" />
    <result column="READ_TIMES" jdbcType="INTEGER" property="readTimes" />
    <result column="LIKED_TIMES" jdbcType="INTEGER" property="likedTimes" />
    <result column="COMMENT_TIMES" jdbcType="INTEGER" property="commentTimes" />
    <result column="USER_ID" jdbcType="VARCHAR" property="userId" />
    <result column="USER_NAME" jdbcType="VARCHAR" property="userName" />
    <result column="NICK_NAME" jdbcType="VARCHAR" property="nickName" />
    <result column="ENABLE_COMMENT" jdbcType="INTEGER" property="enableComment" />
    <result column="STATUS" jdbcType="INTEGER" property="status" />
  </resultMap>
  <resultMap extends="BaseResultMap" id="ResultMapWithBLOBs" type="com.nicefish.model.Post">
    <!--
      WARNING - @mbg.generated
      This element is automatically generated by MyBatis Generator, do not modify.
    -->
    <result column="POST_CONTENT" jdbcType="LONGVARCHAR" property="postContent" />
  </resultMap>
  <sql id="Base_Column_List">
    <!--
      WARNING - @mbg.generated
      This element is automatically generated by MyBatis Generator, do not modify.
    -->
    POST_ID, POST_TITLE, POST_TIME, ORIGINAL_URL, POST_TYPE, LAST_MODIFY_TIME, READ_TIMES, 
    LIKED_TIMES, COMMENT_TIMES, USER_ID, USER_NAME, NICK_NAME, ENABLE_COMMENT, STATUS
  </sql>
  <sql id="Blob_Column_List">
    <!--
      WARNING - @mbg.generated
      This element is automatically generated by MyBatis Generator, do not modify.
    -->
    POST_CONTENT
  </sql>
  <select id="selectByPrimaryKey" parameterType="java.lang.String" resultMap="ResultMapWithBLOBs">
    <!--
      WARNING - @mbg.generated
      This element is automatically generated by MyBatis Generator, do not modify.
    -->
    select 
    <include refid="Base_Column_List" />
    ,
    <include refid="Blob_Column_List" />
    from post
    where POST_ID = #{postId,jdbcType=VARCHAR}
  </select>
  <delete id="deleteByPrimaryKey" parameterType="java.lang.String">
    <!--
      WARNING - @mbg.generated
      This element is automatically generated by MyBatis Generator, do not modify.
    -->
    delete from post
    where POST_ID = #{postId,jdbcType=VARCHAR}
  </delete>
  <insert id="insert" parameterType="com.nicefish.model.Post">
    <!--
      WARNING - @mbg.generated
      This element is automatically generated by MyBatis Generator, do not modify.
    -->
    insert into post (POST_ID, POST_TITLE, POST_TIME, 
      ORIGINAL_URL, POST_TYPE, LAST_MODIFY_TIME, 
      READ_TIMES, LIKED_TIMES, COMMENT_TIMES, 
      USER_ID, USER_NAME, NICK_NAME, 
      ENABLE_COMMENT, STATUS, POST_CONTENT
      )
    values (#{postId,jdbcType=VARCHAR}, #{postTitle,jdbcType=VARCHAR}, #{postTime,jdbcType=TIMESTAMP}, 
      #{originalUrl,jdbcType=VARCHAR}, #{postType,jdbcType=INTEGER}, #{lastModifyTime,jdbcType=TIMESTAMP}, 
      #{readTimes,jdbcType=INTEGER}, #{likedTimes,jdbcType=INTEGER}, #{commentTimes,jdbcType=INTEGER}, 
      #{userId,jdbcType=VARCHAR}, #{userName,jdbcType=VARCHAR}, #{nickName,jdbcType=VARCHAR}, 
      #{enableComment,jdbcType=INTEGER}, #{status,jdbcType=INTEGER}, #{postContent,jdbcType=LONGVARCHAR}
      )
  </insert>
  <insert id="insertSelective" parameterType="com.nicefish.model.Post">
    <!--
      WARNING - @mbg.generated
      This element is automatically generated by MyBatis Generator, do not modify.
    -->
    insert into post
    <trim prefix="(" suffix=")" suffixOverrides=",">
      <if test="postId != null">
        POST_ID,
      </if>
      <if test="postTitle != null">
        POST_TITLE,
      </if>
      <if test="postTime != null">
        POST_TIME,
      </if>
      <if test="originalUrl != null">
        ORIGINAL_URL,
      </if>
      <if test="postType != null">
        POST_TYPE,
      </if>
      <if test="lastModifyTime != null">
        LAST_MODIFY_TIME,
      </if>
      <if test="readTimes != null">
        READ_TIMES,
      </if>
      <if test="likedTimes != null">
        LIKED_TIMES,
      </if>
      <if test="commentTimes != null">
        COMMENT_TIMES,
      </if>
      <if test="userId != null">
        USER_ID,
      </if>
      <if test="userName != null">
        USER_NAME,
      </if>
      <if test="nickName != null">
        NICK_NAME,
      </if>
      <if test="enableComment != null">
        ENABLE_COMMENT,
      </if>
      <if test="status != null">
        STATUS,
      </if>
      <if test="postContent != null">
        POST_CONTENT,
      </if>
    </trim>
    <trim prefix="values (" suffix=")" suffixOverrides=",">
      <if test="postId != null">
        #{postId,jdbcType=VARCHAR},
      </if>
      <if test="postTitle != null">
        #{postTitle,jdbcType=VARCHAR},
      </if>
      <if test="postTime != null">
        #{postTime,jdbcType=TIMESTAMP},
      </if>
      <if test="originalUrl != null">
        #{originalUrl,jdbcType=VARCHAR},
      </if>
      <if test="postType != null">
        #{postType,jdbcType=INTEGER},
      </if>
      <if test="lastModifyTime != null">
        #{lastModifyTime,jdbcType=TIMESTAMP},
      </if>
      <if test="readTimes != null">
        #{readTimes,jdbcType=INTEGER},
      </if>
      <if test="likedTimes != null">
        #{likedTimes,jdbcType=INTEGER},
      </if>
      <if test="commentTimes != null">
        #{commentTimes,jdbcType=INTEGER},
      </if>
      <if test="userId != null">
        #{userId,jdbcType=VARCHAR},
      </if>
      <if test="userName != null">
        #{userName,jdbcType=VARCHAR},
      </if>
      <if test="nickName != null">
        #{nickName,jdbcType=VARCHAR},
      </if>
      <if test="enableComment != null">
        #{enableComment,jdbcType=INTEGER},
      </if>
      <if test="status != null">
        #{status,jdbcType=INTEGER},
      </if>
      <if test="postContent != null">
        #{postContent,jdbcType=LONGVARCHAR},
      </if>
    </trim>
  </insert>
  <update id="updateByPrimaryKeySelective" parameterType="com.nicefish.model.Post">
    <!--
      WARNING - @mbg.generated
      This element is automatically generated by MyBatis Generator, do not modify.
    -->
    update post
    <set>
      <if test="postTitle != null">
        POST_TITLE = #{postTitle,jdbcType=VARCHAR},
      </if>
      <if test="postTime != null">
        POST_TIME = #{postTime,jdbcType=TIMESTAMP},
      </if>
      <if test="originalUrl != null">
        ORIGINAL_URL = #{originalUrl,jdbcType=VARCHAR},
      </if>
      <if test="postType != null">
        POST_TYPE = #{postType,jdbcType=INTEGER},
      </if>
      <if test="lastModifyTime != null">
        LAST_MODIFY_TIME = #{lastModifyTime,jdbcType=TIMESTAMP},
      </if>
      <if test="readTimes != null">
        READ_TIMES = #{readTimes,jdbcType=INTEGER},
      </if>
      <if test="likedTimes != null">
        LIKED_TIMES = #{likedTimes,jdbcType=INTEGER},
      </if>
      <if test="commentTimes != null">
        COMMENT_TIMES = #{commentTimes,jdbcType=INTEGER},
      </if>
      <if test="userId != null">
        USER_ID = #{userId,jdbcType=VARCHAR},
      </if>
      <if test="userName != null">
        USER_NAME = #{userName,jdbcType=VARCHAR},
      </if>
      <if test="nickName != null">
        NICK_NAME = #{nickName,jdbcType=VARCHAR},
      </if>
      <if test="enableComment != null">
        ENABLE_COMMENT = #{enableComment,jdbcType=INTEGER},
      </if>
      <if test="status != null">
        STATUS = #{status,jdbcType=INTEGER},
      </if>
      <if test="postContent != null">
        POST_CONTENT = #{postContent,jdbcType=LONGVARCHAR},
      </if>
    </set>
    where POST_ID = #{postId,jdbcType=VARCHAR}
  </update>
  <update id="updateByPrimaryKeyWithBLOBs" parameterType="com.nicefish.model.Post">
    <!--
      WARNING - @mbg.generated
      This element is automatically generated by MyBatis Generator, do not modify.
    -->
    update post
    set POST_TITLE = #{postTitle,jdbcType=VARCHAR},
      POST_TIME = #{postTime,jdbcType=TIMESTAMP},
      ORIGINAL_URL = #{originalUrl,jdbcType=VARCHAR},
      POST_TYPE = #{postType,jdbcType=INTEGER},
      LAST_MODIFY_TIME = #{lastModifyTime,jdbcType=TIMESTAMP},
      READ_TIMES = #{readTimes,jdbcType=INTEGER},
      LIKED_TIMES = #{likedTimes,jdbcType=INTEGER},
      COMMENT_TIMES = #{commentTimes,jdbcType=INTEGER},
      USER_ID = #{userId,jdbcType=VARCHAR},
      USER_NAME = #{userName,jdbcType=VARCHAR},
      NICK_NAME = #{nickName,jdbcType=VARCHAR},
      ENABLE_COMMENT = #{enableComment,jdbcType=INTEGER},
      STATUS = #{status,jdbcType=INTEGER},
      POST_CONTENT = #{postContent,jdbcType=LONGVARCHAR}
    where POST_ID = #{postId,jdbcType=VARCHAR}
  </update>
  <update id="updateByPrimaryKey" parameterType="com.nicefish.model.Post">
    <!--
      WARNING - @mbg.generated
      This element is automatically generated by MyBatis Generator, do not modify.
    -->
    update post
    set POST_TITLE = #{postTitle,jdbcType=VARCHAR},
      POST_TIME = #{postTime,jdbcType=TIMESTAMP},
      ORIGINAL_URL = #{originalUrl,jdbcType=VARCHAR},
      POST_TYPE = #{postType,jdbcType=INTEGER},
      LAST_MODIFY_TIME = #{lastModifyTime,jdbcType=TIMESTAMP},
      READ_TIMES = #{readTimes,jdbcType=INTEGER},
      LIKED_TIMES = #{likedTimes,jdbcType=INTEGER},
      COMMENT_TIMES = #{commentTimes,jdbcType=INTEGER},
      USER_ID = #{userId,jdbcType=VARCHAR},
      USER_NAME = #{userName,jdbcType=VARCHAR},
      NICK_NAME = #{nickName,jdbcType=VARCHAR},
      ENABLE_COMMENT = #{enableComment,jdbcType=INTEGER},
      STATUS = #{status,jdbcType=INTEGER}
    where POST_ID = #{postId,jdbcType=VARCHAR}
  </update>
</mapper>